main.py
utils.py
visualize_task_csv.py
visualize_task_json.py
flashprof-0.0.17.dist-info/LICENSE
flashprof-0.0.17.dist-info/METADATA
flashprof-0.0.17.dist-info/WHEEL
flashprof-0.0.17.dist-info/entry_points.txt
flashprof-0.0.17.dist-info/top_level.txt
flashprof-0.0.17.dist-info/RECORD
