Metadata-Version: 2.1
Name: flashprof
Version: 0.0.17
Summary: a tool that collects and visualizes TiFlash runtime infomation
Home-page: https://github.com/dragonly/tiflash_mpp_profiler
Author: dragonly
Author-email: liyilongko@gmail.com
License: MIT License        
Platform: UNKNOWN
License-File: LICENSE
Requires-Dist: graphviz
Requires-Dist: paramiko
Requires-Dist: pyyaml
